ttldict
