Metadata-Version: 1.1
Name: ttldict
Version: 0.2.4
Summary: Dictionary with auto-expiring values for caching purposes
Home-page: https://github.com/mobilityhouse/ttldict
Author: Oz Tiram
Author-email: oztiram@mobilityhouse.com
License: MIT
Platform: UNKNOWN
Classifier: Development Status :: 4 - Beta
Classifier: Intended Audience :: Developers
Classifier: License :: OSI Approved :: MIT License
Classifier: Programming Language :: Python :: 3
Classifier: Programming Language :: Python :: 3.4
Classifier: Programming Language :: Python :: 3.5
Classifier: Programming Language :: Python :: 3.6
